README.md
setup.py
spiders/__init__.py
spiders/engine.py
spiders/nasdaq.py
spiders/spider.py
spiders/symbols.py
spiders/util.py
stock_spider.egg-info/PKG-INFO
stock_spider.egg-info/SOURCES.txt
stock_spider.egg-info/dependency_links.txt
stock_spider.egg-info/requires.txt
stock_spider.egg-info/top_level.txt