Metadata-Version: 1.1
Name: stock-spider
Version: 1.0.4
Summary: us stock spider
Home-page: http://xbkaishui.github.io/
Author: xbkaishui
Author-email: xbkaishui@126.com
License: Apache License 2.0
Download-URL: http://pypi.python.org/pypi/stock-spider
Keywords: Spider,US,Stock
Platform: UNKNOWN
Classifier: Development Status :: 4 - Beta
Classifier: Intended Audience :: Developers
Classifier: License :: OSI Approved :: GNU Lesser General Public License v2 or later (LGPLv2+)
Classifier: Topic :: Software Development :: Libraries :: Python Modules
Classifier: Topic :: Office/Business :: Financial :: Investment
